import_class/__init__.py
import_class-0.1.1.dist-info/AUTHORS.rst
import_class-0.1.1.dist-info/LICENSE
import_class-0.1.1.dist-info/METADATA
import_class-0.1.1.dist-info/WHEEL
import_class-0.1.1.dist-info/entry_points.txt
import_class-0.1.1.dist-info/top_level.txt
import_class-0.1.1.dist-info/RECORD
