Metadata-Version: 2.1
Name: import-class
Version: 0.1.1
Summary: A small wrapper to automaticly import a class using importlib
Home-page: https://github.com/jostcrow/import_class
Author: Jorik Kraaikamp
Author-email: jorikkraaikamp@gmail.com
License: MIT license
Keywords: import_class
Platform: UNKNOWN
Classifier: Development Status :: 2 - Pre-Alpha
Classifier: Intended Audience :: Developers
Classifier: License :: OSI Approved :: MIT License
Classifier: Natural Language :: English
Classifier: Programming Language :: Python :: 2
Classifier: Programming Language :: Python :: 2.7
Classifier: Programming Language :: Python :: 3
Classifier: Programming Language :: Python :: 3.4
Classifier: Programming Language :: Python :: 3.5
Classifier: Programming Language :: Python :: 3.6
Classifier: Programming Language :: Python :: 3.7
